CHANGES.txt
MANIFEST.in
MIT-license.txt
README.rst
README.txt
requirements.txt
setup.py
illuminate/__init__.py
illuminate/__main__.py
illuminate/base_parser_class.py
illuminate/control_metrics.py
illuminate/corint_metrics.py
illuminate/error_metrics.py
illuminate/exceptions.py
illuminate/extraction_metrics.py
illuminate/filemaps.py
illuminate/index_metrics.py
illuminate/interop.py
illuminate/metadata.py
illuminate/quality_metrics.py
illuminate/tile_metrics.py
illuminate/utils.py
illuminate.egg-info/PKG-INFO
illuminate.egg-info/SOURCES.txt
illuminate.egg-info/dependency_links.txt
illuminate.egg-info/entry_points.txt
illuminate.egg-info/not-zip-safe
illuminate.egg-info/requires.txt
illuminate.egg-info/top_level.txt