Metadata-Version: 1.0
Name: illuminate
Version: 0.5.9
Summary: Analytics toolkit for Illumina sequencer metrics.
Home-page: https://bitbucket.org/invitae/illuminate
Author: Naomi Most
Author-email: naomi.most@invitae.com
License: MIT
Platform: UNKNOWN
